multiext/__init__.py
multiext/manipulation.py
multiext/parser.py
multiext/path.py
multiext/validation.py
multiext-0.1.2.dist-info/licenses/LICENSE
multiext-0.1.2.dist-info/METADATA
multiext-0.1.2.dist-info/WHEEL
multiext-0.1.2.dist-info/top_level.txt
multiext-0.1.2.dist-info/RECORD
