Metadata-Version: 2.4
Name: multiext
Version: 0.1.2
Summary: A Python library for advanced parsing, validation, and manipulation of multipart file extensions.
Author-email: Henrique Pereira <ikkibr@gmail.com>
License: MIT License
Project-URL: Homepage, https://github.com/ikkebr/multiext
Project-URL: Repository, https://github.com/ikkebr/multiext
Keywords: file extensions,path manipulation,filename parsing,multipart suffix
Classifier: Development Status :: 4 - Beta
Classifier: Intended Audience :: Developers
Classifier: Topic :: Software Development :: Libraries :: Python Modules
Classifier: Topic :: System :: Filesystems
Classifier: Programming Language :: Python :: 3
Classifier: Programming Language :: Python :: 3.10
Classifier: Programming Language :: Python :: 3.11
Classifier: Programming Language :: Python :: 3.12
Classifier: Operating System :: OS Independent
Requires-Python: >=3.10
License-File: LICENSE
Provides-Extra: dev
Requires-Dist: pytest>=6.0; extra == "dev"
Requires-Dist: pytest-cov>=2.0; extra == "dev"
Requires-Dist: build; extra == "dev"
Requires-Dist: twine; extra == "dev"
Dynamic: license-file
